WebError-0.13.dist-info/DESCRIPTION.rst
WebError-0.13.dist-info/METADATA
WebError-0.13.dist-info/RECORD
WebError-0.13.dist-info/WHEEL
WebError-0.13.dist-info/entry_points.txt
WebError-0.13.dist-info/metadata.json
WebError-0.13.dist-info/top_level.txt
weberror/__init__.py
weberror/collector.py
weberror/errormiddleware.py
weberror/eval_template.html
weberror/evalcontext.py
weberror/evalexception.py
weberror/formatter.py
weberror/pdbcapture.py
weberror/pdbcapture_response.html
weberror/reporter.py
weberror/eval-media/debug.js
weberror/eval-media/jquery-1.2.1.min.js
weberror/eval-media/jquery-1.2.3.pack.js
weberror/eval-media/jquery.scrollTo-min.js
weberror/eval-media/jquery.scrollTo.js
weberror/eval-media/minus.jpg
weberror/eval-media/plus.jpg
weberror/eval-media/traceback.css
weberror/exceptions/__init__.py
weberror/exceptions/errormiddleware.py
weberror/util/__init__.py
weberror/util/errorapp.py
weberror/util/escaping.py
weberror/util/security.py
weberror/util/serial_number_generator.py
weberror/util/source_encoding.py
