Metadata-Version: 2.0
Name: WebError
Version: 0.13
Summary: Web Error handling and exception catching
Home-page: https://bitbucket.org/bbangert/weberror
Author: Ben Bangert, Ian Bicking, Mark Ramm
Author-email: invalid@invalid.com
License: MIT
Keywords: wsgi
Platform: UNKNOWN
Classifier: Development Status :: 5 - Production/Stable
Classifier: Intended Audience :: Developers
Classifier: License :: OSI Approved :: MIT License
Classifier: Programming Language :: Python
Classifier: Topic :: Internet :: WWW/HTTP
Classifier: Topic :: Internet :: WWW/HTTP :: Dynamic Content
Classifier: Topic :: Software Development :: Libraries :: Python Modules
Classifier: Topic :: Internet :: WWW/HTTP :: WSGI
Classifier: Topic :: Internet :: WWW/HTTP :: WSGI :: Application
Classifier: Topic :: Internet :: WWW/HTTP :: WSGI :: Middleware
Requires-Dist: Paste (>=1.7.1)
Requires-Dist: Pygments
Requires-Dist: Tempita
Requires-Dist: WebOb
